textual_theme_editor/__init__.py
textual_theme_editor/__main__.py
textual_theme_editor/_app.py
textual_theme_editor/_theme_editor.py
textual_theme_editor/py.typed
textual_theme_editor-0.1.0.dist-info/licenses/LICENSE
textual_theme_editor-0.1.0.dist-info/METADATA
textual_theme_editor-0.1.0.dist-info/WHEEL
textual_theme_editor-0.1.0.dist-info/top_level.txt
textual_theme_editor-0.1.0.dist-info/RECORD
