Metadata-Version: 2.4
Name: textual-theme-editor
Version: 0.1.0
Summary: A theme editor for Textual
Home-page: https://github.com/TomJGooding/textual-theme-editor
Author: TomJGooding
Classifier: Programming Language :: Python :: 3
Classifier: License :: OSI Approved :: GNU General Public License v3 (GPLv3)
Classifier: Operating System :: OS Independent
Requires-Python: >=3.9
License-File: LICENSE
Requires-Dist: textual>=3.3.0
Requires-Dist: textual-colorpicker>=0.1.0
Requires-Dist: tree-sitter>=0.23.0
Requires-Dist: tree-sitter-python>=0.23.0
Provides-Extra: dev
Requires-Dist: black; extra == "dev"
Requires-Dist: flake8; extra == "dev"
Requires-Dist: isort; extra == "dev"
Requires-Dist: mypy; extra == "dev"
Requires-Dist: textual-dev; extra == "dev"
Dynamic: license-file
